[
{"cat" : "Session","pid" :20468,"tid" :4588,"dur" :87,"ts" :5,"ph" : "X","name" :"model_loading_array","args" : {}},
{"cat" : "Session","pid" :20468,"tid" :4588,"dur" :1004,"ts" :201,"ph" : "X","name" :"session_initialization","args" : {}},
{"cat" : "Node","pid" :20468,"tid" :4588,"dur" :43,"ts" :4713,"ph" : "X","name" :"Mul_0_kernel_time","args" : {"parameter_size" : "0","provider" : "CUDAExecutionProvider","op_name" : "Mul","input_type_shape" : [{"float":[2,2]},{"float":[2,2]}],"node_index" : "0","output_type_shape" : [{"float":[2,2]}],"activation_size" : "32","output_size" : "16","thread_scheduling_stats" : {"main_thread": {"thread_pool_name": "session-156-intra-op", "thread_id": "4588", "block_size": [], "core": 4, "Distribution": 0, "DistributionEnqueue": 0, "Run": 0, "Wait": 0, "WaitRevoke": 0}, "sub_threads": {"3284": {"num_run": 0, "core": -1},"18216": {"num_run": 0, "core": -1},"24048": {"num_run": 0, "core": -1},"284": {"num_run": 0, "core": -1},"20728": {"num_run": 0, "core": -1},"19968": {"num_run": 0, "core": -1},"8176": {"num_run": 0, "core": -1}}}}},
{"cat" : "Session","pid" :20468,"tid" :4588,"dur" :76,"ts" :4688,"ph" : "X","name" :"SequentialExecutor::Execute","args" : {}},
{"cat" : "Session","pid" :20468,"tid" :4588,"dur" :2055,"ts" :4444,"ph" : "X","name" :"model_run","args" : {}}
]
